{
  "diploma": {
    "sem1": {
      "engineering mathematics": {
        "matrix and determinants ": {
          "matrix & types": "<a href=\"https://microintel.github.io/missmonk/diploma/sem1/maths/matrix/matrix&types.html\"> Matrix & Types </a>"
        }
      },
      "Fundamentals of Computer": {
        "BASICS\tOF\tLOGIC\tDESIGN": {
          "Introduction\tto\tnumber\tsystem.": {
            "Binary, Octal, Decimal, Hexadecimal": {
              "binary, octal hexadecimal decimal": "<a href=\"https://microintel.github.io/missmonk/diploma/sem1/foc/u1/binary-octal-decimal-hexadecimal.html\"/>"
            }
          }
        },
        "LOGIC\tCIRCUITS": {},
        "INTRODUCTION\tTO\tCOMPUTER\tCONCEPTS": {},
        "INTRODUCTION\tTO\tCOMPUTER\tORGANIZATION\t&\tOPERATING\tSYSTEM": {},
        "INTRODUCTION\tTO\tCOMPUTER\tPROGRAMMING": {}
      },
      "Fundamentals of Electrical and electronics engineering": {},
      "IT Skills": {},
      "Environmental Sustainability": {}
    },
    "sem2": {},
    "sem3": {},
    "sem4": {},
    "sem5": {},
    "sem6": {}
  },
  "engineering": {},
  "Financial": {
    "Stock Market": {
      "Stock Market": {
        "Basics of Stock Market": {
          "Role of Stock Market": {},
          "what is stock market & market cap": {},
          "size of companies": {},
          "what is sensex & nifty": {},
          "Chapter 1": "https://microintel.github.io/missmonk/financial/stock-investing-mastermind/c1.html"
        },
        "How Stock Prices Move?": {
          "Understanding Earnings": {
            "Indian Economy": "tourism industry, dairy industry ,film , aviation, textile, shippment, papar, agriculture industry "
          },
          "True Value and Market Value": {},
          "How Fluctuations in Market Create \rOpportunities": {},
          "Value creation": {},
          "Chapter 2": "https://microintel.github.io/missmonk/financial/stock-investing-mastermind/c2.html"
        },
        "Set-up yourTrading System": {
          "Accounts Required to trade in stock market": "",
          "Chapter 3": "https://microintel.github.io/missmonk/financial/stock-investing-mastermind/c3.html"
        }
      },
      "Stock Research": {
        "Investing vs Trading": {
          "Difference between trading & investing": "",
          "Differences in the mindsets of traders and investors": "",
          "Chapter 4": "https://microintel.github.io/missmonk/financial/stock-investing-mastermind/c4.html"
        },
        "Institutional v/s Retail Investors": {
          "Difference between Institutional & \rRetail Investors": "",
          "Advantages to Institutional \rInvestors over Retail Investors": "",
          "How Diversification Works?": "",
          "Chapter 5": "https://microintel.github.io/missmonk/financial/stock-investing-mastermind/c5.html"
        }
      },
      "Evaluating Companies": {
        "How to generate income ideas": {
          "How Your profession helps generate ideas": "",
          "look around yourself i.e your environment": "",
          "walking & investing": "",
          "analyze what you read": "",
          "use tools like screener": "",
          "what friends and report says": "",
          "Chapter 6": "https://microintel.github.io/missmonk/financial/stock-investing-mastermind/c6.html"
        },
        "Stock Market Report - Where to Find Information": {},
        "How to Read Annual Report": {},
        "Basics of Financial Statment": {},
        "Tools to use": {},
        "How To Analyze a Company": {},
        "Financial Ratios": {}
      },
      "Valuation of Stocks": {},
      "When to Buy & When to Sell?": {},
      "Managing a Portfolio": {},
      "How to Grow your Money?": {}
    }
  }
}